phylo_match/__init__.py
phylo_match/gui.py
phylo_match/definitions/__init__.py
phylo_match/definitions/definitions.py
phylo_match/match/__init__.py
phylo_match/match/match.py
phylo_match-0.1.3.dist-info/COPYING
phylo_match-0.1.3.dist-info/METADATA
phylo_match-0.1.3.dist-info/WHEEL
phylo_match-0.1.3.dist-info/entry_points.txt
phylo_match-0.1.3.dist-info/top_level.txt
phylo_match-0.1.3.dist-info/RECORD
