Metadata-Version: 2.1
Name: phylo-match
Version: 0.1.3
Summary: For matching species databases
Home-page: https://github.com/spearw/phylo-match
Author: William Spear
Author-email: spearw@gmail.com
Classifier: Programming Language :: Python :: 3
Classifier: License :: OSI Approved :: GNU General Public License v3 or later (GPLv3+)
Classifier: Operating System :: OS Independent
Requires-Python: >=3.7
License-File: COPYING
Requires-Dist: diskcache
Requires-Dist: numpy ==1.24.4
Requires-Dist: PyQt6
Requires-Dist: requests
Requires-Dist: wikipedia
Requires-Dist: levenshtein
